README.rst
setup.py
ecstatic/__init__.py
ecstatic/default_config.py
ecstatic/frontend.py
ecstatic.egg-info/PKG-INFO
ecstatic.egg-info/SOURCES.txt
ecstatic.egg-info/dependency_links.txt
ecstatic.egg-info/requires.txt
ecstatic.egg-info/top_level.txt