Metadata-Version: 1.1
Name: ecstatic
Version: 0.4.dev1
Summary: A small flask application to serve files.
Home-page: https://github.com/mbr/ecstatic
Author: Marc Brinkmann
Author-email: git@marcbrinkmann.de
License: MIT
Platform: UNKNOWN
Classifier: Programming Language :: Python :: 2
Classifier: Programming Language :: Python :: 3
